see/__init__.py
see/exceptions.py
see/features.py
see/inspector.py
see/output.py
see/term.py
see/tools.py
see-1.4.0.dist-info/DESCRIPTION.rst
see-1.4.0.dist-info/METADATA
see-1.4.0.dist-info/RECORD
see-1.4.0.dist-info/WHEEL
see-1.4.0.dist-info/metadata.json
see-1.4.0.dist-info/top_level.txt
see-1.4.0.dist-info/zip-safe
